{
    "camera" : {
        "center": [0, 1, 3],
        "target": [0, 0, 0],
        "fov": 90,
        "width": 200,
        "height": 200
    },

    "lights" : [
        {
            "type": "point",
            "pos": [0, 1, 2]
        }
    ],

    "materials" : [
        {
            "type" : "uniform",
            "ka" : [1, 0, 0],
            "kd" : [1, 0, 0],
            "ks" : [1, 0, 0],
            "ns" : 5,
            "ke" : [0, 0, 0],
            "ni" : 1
        },
        {
            "type" : "uniform",
            "ka" : [1, 1, 1],
            "kd" : [1, 1, 1],
            "ks" : [1, 1, 1],
            "ns" : 5,
            "ke" : [0, 0, 0],
            "ni" : 1

        },
        {
            "type" : "uniform",
            "ka" : [0, 1, 0],
            "kd" : [0, 1, 0],
            "ks" : [0, 1, 0],
            "ns" : 5,
            "ke" : [0, 0, 0],
            "ni" : 1
        },
        {
            "type": "uniform",
            "ka" : [0.75, 0.75, 0.75],
            "kd" : [0.75, 0.75, 0.75],
            "ks" : [0.75, 0.75, 0.75],
            "ns" : 5,
            "ke" : [0, 0, 0],
            "ni" : 1
        },
        {
            "type": "uniform",
            "ka" : [1, 1, 1],
            "kd" : [1, 1, 1],
            "ks" : [1, 1, 1],
            "ns" : 5,
            "ke" : [1, 1, 1],
            "ni" : 1
        }
    ],

    "objects" : [
        {
            "type": "sphere",
            "label": "sphere1",
            "center": [-1, 0, 0],
            "radius": 0.5,
            "material": 0
        },
        {
            "type": "sphere",
            "label": "sphere2",
            "center": [0, 0, 0],
            "radius": 0.5,
            "material": 1
        },
        {
            "type": "sphere",
            "label": "sphere3",
            "center": [1, 0, 0],
            "radius": 0.5,
            "material": 2
        },
        {
            "type": "triangle",
            "label": "triangle1",
            "p1": [0, -0.5, 10],
            "p2": [10, -0.5, -10],
            "p3": [-10, -0.5, -10],
            "material": 3
        },
        {
            "type": "triangle",
            "label": "triangle_light",
            "p1": [0, 4, -3],
            "p2": [3, 4, 3],
            "p3": [-3, 4, 3],
            "material": 4
        }

    ],

    "objFiles" : [],

    "mtlDir" : ""
    
}